bancor_research/__init__.py
bancor_research/bancor_emulator/AutoCompoundingRewards.py
bancor_research/bancor_emulator/BNTPool.py
bancor_research/bancor_emulator/BancorNetwork.py
bancor_research/bancor_emulator/BancorNetworkInfo.py
bancor_research/bancor_emulator/BlockNumber.py
bancor_research/bancor_emulator/Constants.py
bancor_research/bancor_emulator/ERC20.py
bancor_research/bancor_emulator/ERC20Burnable.py
bancor_research/bancor_emulator/EnumerableSet.py
bancor_research/bancor_emulator/Fraction.py
bancor_research/bancor_emulator/FractionLibrary.py
bancor_research/bancor_emulator/Math.py
bancor_research/bancor_emulator/MathEx.py
bancor_research/bancor_emulator/NetworkSettings.py
bancor_research/bancor_emulator/Owned.py
bancor_research/bancor_emulator/PendingWithdrawals.py
bancor_research/bancor_emulator/PoolCollection.py
bancor_research/bancor_emulator/PoolCollectionWithdrawal.py
bancor_research/bancor_emulator/PoolToken.py
bancor_research/bancor_emulator/PoolTokenFactory.py
bancor_research/bancor_emulator/ReserveToken.py
bancor_research/bancor_emulator/RewardsMath.py
bancor_research/bancor_emulator/SafeCast.py
bancor_research/bancor_emulator/StandardRewards.py
bancor_research/bancor_emulator/Time.py
bancor_research/bancor_emulator/TokenGovernance.py
bancor_research/bancor_emulator/Vault.py
bancor_research/bancor_emulator/__init__.py
bancor_research/bancor_emulator/config/__init__.py
bancor_research/bancor_emulator/solidity/__init__.py
bancor_research/bancor_emulator/solidity/block.py
bancor_research/bancor_emulator/solidity/error.py
bancor_research/bancor_emulator/solidity/math.py
bancor_research/bancor_emulator/solidity/time.py
bancor_research/bancor_emulator/solidity/types.py
bancor_research/bancor_emulator/solidity/uint/__init__.py
bancor_research/bancor_emulator/solidity/uint/fixed.py
bancor_research/bancor_emulator/solidity/uint/float.py
bancor_research/bancor_emulator/utils/__init__.py
bancor_research/bancor_emulator/v3/__init__.py
bancor_research-3.1.1.dist-info/LICENSE
bancor_research-3.1.1.dist-info/METADATA
bancor_research-3.1.1.dist-info/WHEEL
bancor_research-3.1.1.dist-info/entry_points.txt
bancor_research-3.1.1.dist-info/top_level.txt
bancor_research-3.1.1.dist-info/RECORD
