Metadata-Version: 2.1
Name: bancor-research
Version: 3.1.1
Summary: Bancor v3 python spec, simulator, and emulator library. This is an open-source python package developed by Bancor Research. It is meant to assist in the design, testing, and validating of Bancor v3 behavior.
Home-page: https://github.com/bancorprotocol/research
Author: Bancor Network
Author-email: mike@bancor.network
License: UNKNOWN
Platform: UNKNOWN
License-File: LICENSE
Requires-Dist: pandas
Requires-Dist: numpy
Requires-Dist: networkx
Requires-Dist: cloudpickle
Requires-Dist: pyarrow
Requires-Dist: fastparquet
Requires-Dist: pydantic
Requires-Dist: black
Requires-Dist: jupyter-black
Provides-Extra: complete
